{
  "email_settings": {
    "smtp_server": "smtp.poste.io",
    "smtp_port": 587,
    "sender_email": "inventory@company.com",
    "sender_name": "库存监控系统",
    "use_tls": true
  },
  "recipients": {
    "purchasing_manager": {
      "email": "purchasing.manager@company.com",
      "name": "张经理"
    }
  },
  "email_template": {
    "subject": "【库存预警】{product_name} 库存低于安全阈值",
    "body_template": "尊敬的{recipient_name}，\n\n系统检测到以下产品库存低于安全阈值，请及时处理：\n\n产品信息：\n- 产品名称：{product_name}\n- SKU：{sku}\n- 当前库存：{current_stock}\n- 安全阈值：{threshold}\n- 供应商：{supplier_name}\n- 供应商联系方式：{supplier_contact}\n\n建议采购数量：{suggested_quantity}\n\n请点击以下链接查看采购需求清单：\n{sheets_link}\n\n此邮件由库存监控系统自动发送\n发送时间：{timestamp}"
  },
  "google_sheets_link": "https://docs.google.com/spreadsheets/d/1A2B3C4D5E6F7G8H9I0J/edit"
}